simplecrud/__init__.py
simplecrud/crud.py
simplecrud/sync_crud.py
simplecrud/tests/__init__.py
simplecrud/tests/factories.py
simplecrud/tests/test_crud.py
simplecrud/tests/test_utils.py
simplecrud/utils.py
hexfrost_simplecrud-0.3.0.dist-info/LICENSE
hexfrost_simplecrud-0.3.0.dist-info/METADATA
hexfrost_simplecrud-0.3.0.dist-info/WHEEL
hexfrost_simplecrud-0.3.0.dist-info/RECORD
