Metadata-Version: 2.1
Name: hexfrost-simplecrud
Version: 0.3.0
Summary: Library with operation like (get, create, update, delete) for SQLAlchemy ORM
Author: Ilia Kaziamov
Author-email: kaziamov@outlook.com
Requires-Python: >=3.8.1,<4.0
Classifier: Programming Language :: Python :: 3
Classifier: Programming Language :: Python :: 3.9
Classifier: Programming Language :: Python :: 3.10
Classifier: Programming Language :: Python :: 3.11
Classifier: Programming Language :: Python :: 3.12
Requires-Dist: sqlalchemy (>=2.0.0,<3.0.0)
